flacker/__init__.py
flacker/engine.py
flacker/models.py
flacker/operations.py
flacker/patterns.py
flacker/apis/__init__.py
flacker/apis/hue_api.py
flacker/apis/hue_entertainment_api.py
flacker/apis/log_api.py
flacker/apis/multi_api.py
flacker/apis/plot_api.py
flacker-0.1.0.dist-info/licenses/LICENSE
flacker-0.1.0.dist-info/METADATA
flacker-0.1.0.dist-info/WHEEL
flacker-0.1.0.dist-info/top_level.txt
flacker-0.1.0.dist-info/RECORD
